frechet_music_distance/__init__.py
frechet_music_distance/__main__.py
frechet_music_distance/fmd.py
frechet_music_distance/memory.py
frechet_music_distance/utils.py
frechet_music_distance/dataset_loaders/__init__.py
frechet_music_distance/dataset_loaders/abc_loader.py
frechet_music_distance/dataset_loaders/dataset_loader.py
frechet_music_distance/dataset_loaders/midi_as_mtf_loader.py
frechet_music_distance/dataset_loaders/utils.py
frechet_music_distance/gaussian_estimators/__init__.py
frechet_music_distance/gaussian_estimators/bootstrapping_estimator.py
frechet_music_distance/gaussian_estimators/gaussian_estimator.py
frechet_music_distance/gaussian_estimators/leodit_wolf_estimator.py
frechet_music_distance/gaussian_estimators/max_likelihood_estimator.py
frechet_music_distance/gaussian_estimators/oas_estimator.py
frechet_music_distance/gaussian_estimators/shrikage_estimator.py
frechet_music_distance/gaussian_estimators/utils.py
frechet_music_distance/models/__init__.py
frechet_music_distance/models/feature_extractor.py
frechet_music_distance/models/utils.py
frechet_music_distance/models/clamp/__init__.py
frechet_music_distance/models/clamp/clamp_extractor.py
frechet_music_distance/models/clamp/clamp_model.py
frechet_music_distance/models/clamp/clamp_utils.py
frechet_music_distance/models/clamp2/__init__.py
frechet_music_distance/models/clamp2/clamp2_extractor.py
frechet_music_distance/models/clamp2/clamp2_model.py
frechet_music_distance/models/clamp2/config.py
frechet_music_distance/models/clamp2/m3_patch_encoder.py
frechet_music_distance/models/clamp2/m3_patchilizer.py
frechet_music_distance-1.0.0.dist-info/LICENSE.txt
frechet_music_distance-1.0.0.dist-info/METADATA
frechet_music_distance-1.0.0.dist-info/WHEEL
frechet_music_distance-1.0.0.dist-info/entry_points.txt
frechet_music_distance-1.0.0.dist-info/top_level.txt
frechet_music_distance-1.0.0.dist-info/RECORD
