Metadata-Version: 2.2
Name: frechet_music_distance
Version: 1.0.0
Summary: A library for computing Frechet Music Distance.
Author: jryban
Maintainer: jryban
License: MIT License
Project-URL: Homepage, https://github.com/jryban/frechet-music-distance
Project-URL: Repository, https://github.com/jryban/frechet-music-distance.git
Keywords: frechet,music,distance,metric,symbolic,evaluation,generative,frechet music distance,symbolic music,frechet distance,music metric,symbolic music evaluation
Classifier: Programming Language :: Python :: 3
Classifier: License :: OSI Approved :: MIT License
Classifier: Operating System :: OS Independent
Requires-Python: >=3.9
License-File: LICENSE.txt
Requires-Dist: abctoolkit
Requires-Dist: accelerate
Requires-Dist: joblib
Requires-Dist: numpy
Requires-Dist: tqdm
Requires-Dist: scipy
Requires-Dist: requests
Requires-Dist: mido
Requires-Dist: transformers
Requires-Dist: torch
Requires-Dist: unidecode
Requires-Dist: scikit-learn
